paperbase/__init__.py
paperbase/auth.py
paperbase/config.py
paperbase/pdb.py
paperbase/addon/auth_handler.exe
paperbase-2.0.dist-info/METADATA
paperbase-2.0.dist-info/WHEEL
paperbase-2.0.dist-info/top_level.txt
paperbase-2.0.dist-info/RECORD
