Metadata-Version: 2.4
Name: paperbase
Version: 2.0
Summary: Simple file-based database with user auth
Author: PaperCode
Author-email: aritra.paper.code@gmail.com
License: MIT
Classifier: Programming Language :: Python :: 3
Dynamic: author
Dynamic: author-email
Dynamic: classifier
Dynamic: description
Dynamic: description-content-type
Dynamic: license
Dynamic: summary
